karolis_s_mod1_atsiskaitymas/__init__.py
karolis_s_mod1_atsiskaitymas/main.py
karolis_s_mod1_atsiskaitymas/testai.py
karolis_s_mod1_atsiskaitymas-1.0.1.dist-info/METADATA
karolis_s_mod1_atsiskaitymas-1.0.1.dist-info/WHEEL
karolis_s_mod1_atsiskaitymas-1.0.1.dist-info/entry_points.txt
karolis_s_mod1_atsiskaitymas-1.0.1.dist-info/top_level.txt
karolis_s_mod1_atsiskaitymas-1.0.1.dist-info/RECORD
