Metadata-Version: 2.1
Name: karolis_s_mod1_atsiskaitymas
Version: 1.0.1
Author: Karolis
Author-email: karolis.skruibis@codeacademylt.onmicrosoft.com
